ghnova/__init__.py
ghnova/__main__.py
ghnova/version.py
ghnova/cli/__init__.py
ghnova/cli/main.py
ghnova/cli/config/__init__.py
ghnova/cli/config/add.py
ghnova/cli/config/delete.py
ghnova/cli/config/list.py
ghnova/cli/config/main.py
ghnova/cli/config/update.py
ghnova/cli/issue/__init__.py
ghnova/cli/issue/create.py
ghnova/cli/issue/get.py
ghnova/cli/issue/list.py
ghnova/cli/issue/lock.py
ghnova/cli/issue/main.py
ghnova/cli/issue/unlock.py
ghnova/cli/issue/update.py
ghnova/cli/repository/__init__.py
ghnova/cli/repository/list.py
ghnova/cli/repository/main.py
ghnova/cli/user/__init__.py
ghnova/cli/user/ctx_info.py
ghnova/cli/user/get.py
ghnova/cli/user/list.py
ghnova/cli/user/main.py
ghnova/cli/user/update.py
ghnova/cli/utils/__init__.py
ghnova/cli/utils/auth.py
ghnova/client/__init__.py
ghnova/client/async_github.py
ghnova/client/base.py
ghnova/client/github.py
ghnova/config/__init__.py
ghnova/config/manager.py
ghnova/config/model.py
ghnova/issue/__init__.py
ghnova/issue/async_issue.py
ghnova/issue/base.py
ghnova/issue/issue.py
ghnova/repository/__init__.py
ghnova/repository/async_repository.py
ghnova/repository/base.py
ghnova/repository/repository.py
ghnova/resource/__init__.py
ghnova/resource/async_resource.py
ghnova/resource/resource.py
ghnova/user/__init__.py
ghnova/user/async_user.py
ghnova/user/base.py
ghnova/user/user.py
ghnova/utils/__init__.py
ghnova/utils/log.py
ghnova/utils/response.py
ghnova-0.3.0.dist-info/METADATA
ghnova-0.3.0.dist-info/WHEEL
ghnova-0.3.0.dist-info/entry_points.txt
ghnova-0.3.0.dist-info/licenses/LICENSE
ghnova-0.3.0.dist-info/RECORD
