Metadata-Version: 2.4
Name: ghnova
Version: 0.3.0
Summary: A Python package for interacting with the GitHub API, offering a simple interface to access repositories, users, organizations, issues, and more for automation and data management.
Project-URL: Documentation, https://isaac-cf-wong.github.io/ghnova
Project-URL: Source, https://github.com/isaac-cf-wong/ghnova
Project-URL: Tracker, https://github.com/isaac-cf-wong/ghnova/issues
Project-URL: Home, https://github.com/isaac-cf-wong/ghnova
Project-URL: Release Notes, https://github.com/isaac-cf-wong/ghnova/releases
Author-email: "Isaac C. F. Wong" <isaac.cf.wong@gmail.com>
License-File: LICENSE
Classifier: Development Status :: 3 - Alpha
Classifier: Intended Audience :: Developers
Classifier: License :: OSI Approved :: MIT License
Classifier: Programming Language :: Python :: 3 :: Only
Classifier: Programming Language :: Python :: 3.10
Classifier: Programming Language :: Python :: 3.11
Classifier: Programming Language :: Python :: 3.12
Requires-Python: >=3.10
Requires-Dist: aiohttp==3.13.3
Requires-Dist: pydantic==2.12.5
Requires-Dist: typer==0.21.1
Provides-Extra: dev
Requires-Dist: black; extra == 'dev'
Requires-Dist: flake8; extra == 'dev'
Requires-Dist: pre-commit; extra == 'dev'
Requires-Dist: pytest; extra == 'dev'
Provides-Extra: docs
Requires-Dist: mike; extra == 'docs'
Requires-Dist: mkdocs; extra == 'docs'
Requires-Dist: mkdocs-gen-files; extra == 'docs'
Requires-Dist: mkdocs-literate-nav; extra == 'docs'
Requires-Dist: mkdocs-material; extra == 'docs'
Requires-Dist: mkdocs-section-index; extra == 'docs'
Requires-Dist: mkdocstrings[python]; extra == 'docs'
Provides-Extra: test
Requires-Dist: bandit[toml]==1.9.3; extra == 'test'
Requires-Dist: black==26.1.0; extra == 'test'
Requires-Dist: check-manifest==0.51; extra == 'test'
Requires-Dist: flake8; extra == 'test'
Requires-Dist: flake8-bugbear==25.11.29; extra == 'test'
Requires-Dist: flake8-docstrings; extra == 'test'
Requires-Dist: flake8-formatter-junit-xml; extra == 'test'
Requires-Dist: flake8-pyproject; extra == 'test'
Requires-Dist: pre-commit==4.5.1; extra == 'test'
Requires-Dist: pytest-asyncio==1.3.0; extra == 'test'
Requires-Dist: pytest-cov==7.0.0; extra == 'test'
Requires-Dist: pytest-github-actions-annotate-failures; extra == 'test'
Requires-Dist: pytest-mock<3.15.2; extra == 'test'
Requires-Dist: pytest-runner; extra == 'test'
Requires-Dist: pytest==9.0.2; extra == 'test'
Requires-Dist: shellcheck-py==0.11.0.1; extra == 'test'
